tommygtst/__init__.py
tommygtst-0.1.0.dist-info/METADATA
tommygtst-0.1.0.dist-info/WHEEL
tommygtst-0.1.0.dist-info/RECORD
