Metadata-Version: 2.1
Name: tommygtst
Version: 0.1.0
Summary: test pip
Author: tommy
Author-email: jujpl@outlook.com
Requires-Python: >=3.10,<4.0
Classifier: Programming Language :: Python :: 3
Classifier: Programming Language :: Python :: 3.10
Classifier: Programming Language :: Python :: 3.11
